rattledin/__init__.py
rattledin/driver.py
rattledin/errors.py
rattledin/results.py
rattledin/commands/__init__.py
rattledin/commands/chat.py
rattledin/managers/__init__.py
rattledin/managers/chat.py
rattledin-0.0.1.dist-info/LICENSE
rattledin-0.0.1.dist-info/METADATA
rattledin-0.0.1.dist-info/WHEEL
rattledin-0.0.1.dist-info/top_level.txt
rattledin-0.0.1.dist-info/RECORD
