Metadata-Version: 2.1
Name: rattledin
Version: 0.0.1
Summary: A asynchronous library to communicate with Linkedin
Home-page: https://github.com/jabolina/rattledin.git
Author: Jose Augusto Bolina
Author-email: joseaugusto.bolina@hotmail.com
License: MIT
Keywords: Chat Bot Linkedin Asynchronous
Platform: UNKNOWN
Classifier: Development Status :: 3 - Alpha
Classifier: Intended Audience :: Developers
Classifier: Topic :: Communications :: Chat
Classifier: Natural Language :: Portuguese (Brazilian)
Classifier: License :: OSI Approved :: MIT License
Classifier: Programming Language :: Python :: 3.6
Classifier: Topic :: Communications :: Chat
Requires-Dist: aiohttp (==3.5.4)
Requires-Dist: async-timeout (==3.0.1)
Requires-Dist: attrs (==18.2.0)
Requires-Dist: certifi (==2018.8.24)
Requires-Dist: chardet (==3.0.4)
Requires-Dist: idna (==2.7)
Requires-Dist: idna-ssl (==1.1.0)
Requires-Dist: multidict (==4.5.2)
Requires-Dist: requests (==2.19.1)
Requires-Dist: typing-extensions (==3.7.2)
Requires-Dist: urllib3 (==1.23)
Requires-Dist: yarl (==1.3.0)
Provides-Extra: linkedin
Requires-Dist: linkedin-api ; extra == 'linkedin'
